{
  "main": {
    "id": "dc5449299677b9cd",
    "type": "split",
    "children": [
      {
        "id": "c6d400cf2bf768f1",
        "type": "split",
        "children": [
          {
            "id": "fed3941611d5a34a",
            "type": "tabs",
            "dimension": 62.33333333333333,
            "children": [
              {
                "id": "159e3d067e7426a3",
                "type": "leaf",
                "pinned": true,
                "state": {
                  "type": "obsidian-projects",
                  "state": {},
                  "pinned": true
                }
              },
              {
                "id": "aa82f8c4b852bab7",
                "type": "leaf",
                "state": {
                  "type": "markdown",
                  "state": {
                    "file": "Processes/7.3 Determine Budget.md",
                    "mode": "source",
                    "backlinks": true,
                    "source": false
                  }
                }
              }
            ],
            "currentTab": 1
          },
          {
            "id": "d30cbe78abd001e8",
            "type": "split",
            "dimension": 37.666666666666664,
            "children": [
              {
                "id": "80158b254f45e775",
                "type": "tabs",
                "children": [
                  {
                    "id": "f584f962f0bfbac7",
                    "type": "leaf",
                    "pinned": true,
                    "state": {
                      "type": "graph",
                      "state": {},
                      "pinned": true
                    }
                  },
                  {
                    "id": "ceb57b8ab0084554",
                    "type": "leaf",
                    "pinned": true,
                    "state": {
                      "type": "pdf",
                      "state": {
                        "file": "_attachments/PMBOK Processes Flow by Ricardo Vargas.pdf"
                      },
                      "pinned": true
                    }
                  }
                ]
              },
              {
                "id": "7cf61c926007bd1a",
                "type": "tabs",
                "children": [
                  {
                    "id": "1db08ea8faea650a",
                    "type": "leaf",
                    "state": {
                      "type": "3d_graph_view",
                      "state": {}
                    }
                  }
                ]
              }
            ],
            "direction": "vertical"
          }
        ],
        "direction": "horizontal"
      }
    ],
    "direction": "vertical"
  },
  "left": {
    "id": "a8a9616ba25f9573",
    "type": "split",
    "children": [
      {
        "id": "d6f1264d5c703eb3",
        "type": "tabs",
        "children": [
          {
            "id": "3632dba8c6711c61",
            "type": "leaf",
            "state": {
              "type": "file-explorer",
              "state": {
                "sortOrder": "alphabetical"
              }
            }
          },
          {
            "id": "b9269b42da62cfda",
            "type": "leaf",
            "state": {
              "type": "search",
              "state": {
                "query": "\"earned value management\"",
                "matchingCase": false,
                "explainSearch": false,
                "collapseAll": false,
                "extraContext": false,
                "sortOrder": "alphabetical"
              }
            }
          },
          {
            "id": "ce2f4e0758d6bd41",
            "type": "leaf",
            "state": {
              "type": "bookmarks",
              "state": {}
            }
          }
        ]
      }
    ],
    "direction": "horizontal",
    "width": 299.5,
    "collapsed": true
  },
  "right": {
    "id": "8ac93f681408532f",
    "type": "split",
    "children": [
      {
        "id": "77793a40bf34dd40",
        "type": "tabs",
        "children": [
          {
            "id": "fd965bc9e993acf2",
            "type": "leaf",
            "state": {
              "type": "advanced-tables-toolbar",
              "state": {}
            }
          },
          {
            "id": "c461271a4d5a59c0",
            "type": "leaf",
            "state": {
              "type": "tag",
              "state": {
                "sortOrder": "frequency",
                "useHierarchy": true
              }
            }
          },
          {
            "id": "8894ec8e635a8c07",
            "type": "leaf",
            "state": {
              "type": "outline",
              "state": {
                "file": "Processes/7.3 Determine Budget.md"
              }
            }
          },
          {
            "id": "adc5fd924ebb1eb5",
            "type": "leaf",
            "state": {
              "type": "file-properties",
              "state": {
                "file": "Processes/7.3 Determine Budget.md"
              }
            }
          }
        ],
        "currentTab": 3
      }
    ],
    "direction": "horizontal",
    "width": 328.5
  },
  "left-ribbon": {
    "hiddenItems": {
      "card-board:CardBoard": false,
      "switcher:Open quick switcher": false,
      "graph:Open graph view": false,
      "command-palette:Open command palette": false,
      "canvas:Create new canvas": false,
      "templater-obsidian:Templater": false,
      "table-editor-obsidian:Advanced Tables Toolbar": false,
      "obsidian-projects:Open projects": false,
      "3d-graph:3D Graph": false,
      "workspaces:Manage workspace layouts": false,
      "obsidian42-brat:BRAT": false
    }
  },
  "active": "aa82f8c4b852bab7",
  "lastOpenFiles": [
    "Artefacts/Cost Estimates.md",
    "Processes/7.2 Estimate Costs.md",
    "Artefacts/Basis of Estimates.md",
    "Tools and Techniques/Three-Point Estimating.md",
    "Tools and Techniques/Cost of Quality.md",
    "_attachments/Cost of Quality.png",
    "Tools and Techniques/Reserve Analysis.md",
    "Tools and Techniques/Expert Judgment Topics/Cost Estimating Methods.md",
    "Influences/Cost Estimating Templates.md",
    "Influences/Currency Exchange Rates and Inflation.md",
    "Artefacts/Work Performance Report.md",
    "Artefacts/Product, Service, Result Transition.md",
    "Artefacts/Procurement Documentation.md",
    "Artefacts/Final Report.md",
    "Tools and Techniques/Groups/Decision-Making.md",
    "Tools and Techniques/Meetings/Cost Planning Meeting.md",
    "Processes/7.1 Plan Cost Management.md",
    "Artefacts/Project Management Plan/Subsidiary Management Plans/Cost Management Plan.md",
    "Artefacts/Work Breakdown Structure.md",
    "Mics/Practice Standard for Earned Value Management.md",
    "Processes/6.1 Plan Schedule Management.md",
    "Tools and Techniques/Meetings/Schedule Planning Meeting.md",
    "Processes/6.4 Estimate Activity Durations.md",
    "Tools and Techniques/Alternatives Analysis.md",
    "Tools and Techniques/Earned Value Analysis.md",
    "Influences/Cost Estimating and Budgeting.md",
    "Influences/Financial Databases.md",
    "_attachments/Example Probability and Impact Matrix with Scoring Scheme.png",
    "_attachments/Example of Definitions for Probability and Impacts.png",
    "_attachments/Pasted image 20240204192107.png",
    "_attachments/Project Schedule Presentations Examples.png",
    "_attachments/Relationship Between Product Vision, Release Planning, and Iteration Planning.png",
    "_attachments/Schedule Compression Comparison.png",
    "_attachments/Example Probability Distribution of a Target Milestone.png",
    "_attachments/Resource Leveling.png",
    "_attachments/Example of Critical Path Method.png",
    "Mics",
    "_attachments/PMBOK Processes Flow by Ricardo Vargas.pdf",
    "Project Management Plan/Baselines/_attachments",
    "Project Management Plan/Baselines/Components",
    "Artefacts/Project Management Plan/Baselines",
    "Artefacts/Project Management Plan/Subsidiary Management Plans",
    "Tools and Techniques/Meetings",
    "_templates",
    "Tools and Techniques/Expert Judgment Topics",
    "Influences",
    "Untitled.canvas",
    "Untitled 6.canvas",
    "Untitled 5.canvas",
    "Untitled 4.canvas",
    "Untitled 3.canvas",
    "Untitled 2.canvas",
    "Untitled 1.canvas"
  ]
}